ai_runner_hjy/__init__.py
ai_runner_hjy/__main__.py
ai_runner_hjy/cfg_tool.py
ai_runner_hjy/cli.py
ai_runner_hjy/dev_server.py
ai_runner_hjy/doctor.py
ai_runner_hjy/init_check.py
ai_runner_hjy/providers.py
ai_runner_hjy/quickstart.py
ai_runner_hjy/route.py
ai_runner_hjy/run.py
ai_runner_hjy/runner.py
ai_runner_hjy/config_ops/__init__.py
ai_runner_hjy/config_ops/fullstack_gen.py
ai_runner_hjy/core/auth.py
ai_runner_hjy/core/build.py
ai_runner_hjy/core/config.py
ai_runner_hjy/core/crud.py
ai_runner_hjy/core/crypto_utils.py
ai_runner_hjy/core/db.py
ai_runner_hjy/core/errors.py
ai_runner_hjy/core/logs.py
ai_runner_hjy/core/oss.py
ai_runner_hjy/core/policy.py
ai_runner_hjy/core/quota.py
ai_runner_hjy/core/redact.py
ai_runner_hjy/core/request.py
ai_runner_hjy/core/routing.py
ai_runner_hjy/core/types.py
ai_runner_hjy/examples/__init__.py
ai_runner_hjy-0.0.3.dist-info/licenses/LICENSE
ai_runner_hjy-0.0.3.dist-info/METADATA
ai_runner_hjy-0.0.3.dist-info/WHEEL
ai_runner_hjy-0.0.3.dist-info/entry_points.txt
ai_runner_hjy-0.0.3.dist-info/top_level.txt
ai_runner_hjy-0.0.3.dist-info/RECORD
