Metadata-Version: 2.4
Name: ai-runner-hjy
Version: 0.0.3
Summary: DB-config driven OpenAI-compatible AI runner with auditing, CLI + importable API
Author: hjy
License: MIT
Project-URL: Homepage, https://example.com
Keywords: openai,chat,audit,mysql,ai,runner
Classifier: License :: OSI Approved :: MIT License
Classifier: Programming Language :: Python :: 3
Classifier: Programming Language :: Python :: 3.9
Classifier: Programming Language :: Python :: 3.10
Classifier: Programming Language :: Python :: 3.11
Classifier: Programming Language :: Python :: 3.12
Classifier: Intended Audience :: Developers
Classifier: Topic :: Software Development :: Libraries
Requires-Python: >=3.9
License-File: LICENSE
Requires-Dist: pydantic<3,>=2.0
Requires-Dist: pydantic-settings<3,>=2.2
Requires-Dist: httpx<1,>=0.27
Requires-Dist: loguru<1,>=0.7
Requires-Dist: mysql-connector-python<9,>=8.3
Requires-Dist: cryptography<43,>=41
Requires-Dist: oss2<3,>=2.18
Provides-Extra: test
Requires-Dist: pytest>=7; extra == "test"
Requires-Dist: pytest-cov>=4; extra == "test"
Provides-Extra: web
Requires-Dist: fastapi>=0.111; extra == "web"
Requires-Dist: uvicorn>=0.30; extra == "web"
Dynamic: license-file
